codespell_lib/__init__.py
codespell_lib/__main__.py
codespell_lib/_codespell.py
codespell_lib/_spellchecker.py
codespell_lib/_text_util.py
codespell_lib/_version.py
codespell_lib/py.typed
codespell_lib/data/__init__.py
codespell_lib/data/dictionary.txt
codespell_lib/data/dictionary_code.txt
codespell_lib/data/dictionary_en-GB_to_en-US.txt
codespell_lib/data/dictionary_informal.txt
codespell_lib/data/dictionary_names.txt
codespell_lib/data/dictionary_rare.txt
codespell_lib/data/dictionary_usage.txt
codespell_lib/data/linux-kernel.exclude
codespell_lib/tests/__init__.py
codespell_lib/tests/test_basic.py
codespell_lib/tests/test_dictionary.py
codespell_lib/tests/data/en_GB-additional.wordlist
codespell_lib/tests/data/en_US-additional.wordlist
codespell-2.4.0.dist-info/COPYING
codespell-2.4.0.dist-info/METADATA
codespell-2.4.0.dist-info/WHEEL
codespell-2.4.0.dist-info/entry_points.txt
codespell-2.4.0.dist-info/top_level.txt
codespell-2.4.0.dist-info/RECORD
