Metadata-Version: 2.2
Name: codespell
Version: 2.4.0
Summary: Fix common misspellings in text files
Author-email: Lucas De Marchi <lucas.de.marchi@gmail.com>
License: GPL-2.0-only
Project-URL: homepage, https://github.com/codespell-project/codespell
Project-URL: repository, https://github.com/codespell-project/codespell
Classifier: Intended Audience :: Developers
Classifier: License :: OSI Approved
Classifier: Programming Language :: Python
Classifier: Topic :: Software Development
Classifier: Operating System :: Microsoft :: Windows
Classifier: Operating System :: POSIX
Classifier: Operating System :: Unix
Classifier: Operating System :: MacOS
Classifier: Programming Language :: Python
Classifier: Programming Language :: Python :: 3
Classifier: Programming Language :: Python :: 3 :: Only
Classifier: Programming Language :: Python :: 3.8
Classifier: Programming Language :: Python :: 3.9
Classifier: Programming Language :: Python :: 3.10
Classifier: Programming Language :: Python :: 3.11
Classifier: Programming Language :: Python :: 3.12
Classifier: Programming Language :: Python :: 3.13
Requires-Python: >=3.8
License-File: COPYING
Provides-Extra: dev
Requires-Dist: build; extra == "dev"
Requires-Dist: chardet; extra == "dev"
Requires-Dist: pre-commit; extra == "dev"
Requires-Dist: pytest; extra == "dev"
Requires-Dist: pytest-cov; extra == "dev"
Requires-Dist: pytest-dependency; extra == "dev"
Requires-Dist: Pygments; extra == "dev"
Requires-Dist: ruff; extra == "dev"
Requires-Dist: tomli; extra == "dev"
Requires-Dist: twine; extra == "dev"
Provides-Extra: hard-encoding-detection
Requires-Dist: chardet; extra == "hard-encoding-detection"
Provides-Extra: toml
Requires-Dist: tomli; python_version < "3.11" and extra == "toml"
Provides-Extra: types
Requires-Dist: chardet>=5.1.0; extra == "types"
Requires-Dist: mypy; extra == "types"
Requires-Dist: pytest; extra == "types"
Requires-Dist: pytest-cov; extra == "types"
Requires-Dist: pytest-dependency; extra == "types"
